py4shared.py
setup.py
py4shared.egg-info/PKG-INFO
py4shared.egg-info/SOURCES.txt
py4shared.egg-info/dependency_links.txt
py4shared.egg-info/requires.txt
py4shared.egg-info/top_level.txt