Metadata-Version: 1.0
Name: py4shared
Version: 1.1
Summary: 4shared download manager
Home-page: https://github.com/sh4r3m4n/py4shared
Author: Matías Lang
Author-email: shareman1204@gmail.com
License: GPL3
Platform: UNKNOWN
